MANIFEST.in
setup.py
src/duckietown_uplan/__init__.py
src/duckietown_uplan/plan_main.py
src/duckietown_uplan.egg-info/PKG-INFO
src/duckietown_uplan.egg-info/SOURCES.txt
src/duckietown_uplan.egg-info/dependency_links.txt
src/duckietown_uplan.egg-info/entry_points.txt
src/duckietown_uplan.egg-info/not-zip-safe
src/duckietown_uplan.egg-info/top_level.txt
src/duckietown_uplan/algo/__init__.py
src/duckietown_uplan/algo/constants.py
src/duckietown_uplan/algo/observations.py
src/duckietown_uplan/algo/path_planning.py
src/duckietown_uplan/algo/utils.py
src/duckietown_uplan/algo/velocity_profiling.py
src/duckietown_uplan/cli/__init__.py
src/duckietown_uplan/cli/foo_cli.py
src/duckietown_uplan/data/__init__.py
src/duckietown_uplan/data/apriltagsDB.yaml
src/duckietown_uplan/environment/__init__.py
src/duckietown_uplan/environment/constant.py
src/duckietown_uplan/environment/duckie.py
src/duckietown_uplan/environment/duckie_town.py
src/duckietown_uplan/environment/footprint_table.py
src/duckietown_uplan/environment/utils.py
src/duckietown_uplan/graph_utils/__init__.py
src/duckietown_uplan/graph_utils/augmentation.py
src/duckietown_uplan/graph_utils/constants.py
src/duckietown_uplan/graph_utils/segmentify.py
src/duckietown_uplan/simulation/__init__.py
src/duckietown_uplan/simulation/simulation.py
src/duckietown_uplan_tests/__init__.py
src/duckietown_uplan_tests/test1.py
src/duckietown_uplan_tests/test2.py
src/duckietown_uplan_tests/test_sim.py