Metadata-Version: 1.1
Name: duckietown-uplan
Version: 1.0.0
Summary: This project aims to plan a path for a duckiebot while taking into account various sources of uncertainty.
Home-page: UNKNOWN
Author: UNKNOWN
Author-email: UNKNOWN
License: UNKNOWN
Download-URL: http://github.com/duckietown/duckietown-uplan/tarball/1.0.0
Platform: UNKNOWN
Classifier: Development Status :: 3 - Alpha
Classifier: Programming Language :: Python :: 2
Classifier: Programming Language :: Python :: 3
